README.md
setup.py
ky/__init__.py
ky/api.py
ky/base.py
ky/comm.py
ky/order.py
ky_sdk.egg-info/PKG-INFO
ky_sdk.egg-info/SOURCES.txt
ky_sdk.egg-info/dependency_links.txt
ky_sdk.egg-info/requires.txt
ky_sdk.egg-info/top_level.txt
ky_sdk.egg-info/zip-safe